grif3.v
// Griffin, Faith Juliamae O. - S11

module BCD_D(Q,D,clk,rst);
output reg Q;
input D, clk, rst;

always @(posedge clk, negedge rst)
	if (rst == 0) 
		Q <= 4'b0000;
	else
		Q <= D;
endmodule

module BCD_main(A,B,C,D,X,clock,reset);
output A,B,C,D;
input X, clock,reset;
wire DA, DB, DC, DD;

assign DA = (A & ~B & ~C & ~D & ~X) | (~A & B & C & D & ~X) | (~A & ~B & ~C & ~D & X) | (A & ~B & ~C & D & X);
assign DB = (~A & B & ~C & ~X) | (~A & B & D & X) | (~A & B & C & ~D) | (A & ~B & ~C & ~D & X) | (~A & ~B & C & D & ~X);
assign DC = (~A & ~C & D & ~X) | (~A & C & ~D & ~X) | (~A & C & D & X) | (~A & B & ~C & ~D & X) | (A & ~B & ~C & ~D & X);
assign DD = (~A & ~D) | (A & ~B & ~C & ~D);

BCD_D F1(A, DA, clock, reset);
BCD_D F2(B, DB, clock, reset);
BCD_D F3(C, DC, clock, reset);
BCD_D F4(D, DD, clock, reset);
endmodule

grif3_tb.v
// Griffin, Faith Juliamae O. - S11

module BCD_tb();
wire t_A, t_B, t_C, t_D;
reg t_X, t_clk, t_reset; 

BCD_main dut(t_A,t_B,t_C,t_D,t_X,t_clk,t_reset);

initial
	begin
		t_clk = 1'b0;
		forever #5 t_clk = ~t_clk;
	end

initial
	begin
		t_reset = 1'b0;
		#10 t_reset = 1'b1;
	end

initial
	begin
		t_X = 1'b0;
		#50 t_X = 1'b0;#10 t_X = 1'b0;#10 t_X = 1'b0;#10 t_X = 1'b0;#10 t_X = 1'b0;#10 t_X = 1'b0;
		#10 t_X = 1'b1;#10 t_X = 1'b1;#10 t_X = 1'b1;#10 t_X = 1'b1;#10 t_X = 1'b1;
	end

initial
	begin
		$display("Program by Faith Juliamae O. Griffin - S11");
		$display("Sequential Circuit Specification: Up-down BCD counter using D Flip Flop");
		$monitor("t=%0d\tclk=%b\treset=%b\t\tX=%b\tA=%b\tB=%b\tC=%b\tD=%b",$time,t_clk,t_reset,t_X,t_A,t_B,t_C,t_D);
		$dumpfile("grif3.vcd");
		$dumpvars();
	end

initial #205 $finish;
endmodule

grif3.vcd
$date
	Mon Jul 04 02:12:52 2022
$end
$version
	Icarus Verilog
$end
$timescale
	1s
$end
$scope module BCD_tb $end
$var wire 1 ! t_D $end
$var wire 1 " t_C $end
$var wire 1 # t_B $end
$var wire 1 $ t_A $end
$var reg 1 % t_X $end
$var reg 1 & t_clk $end
$var reg 1 ' t_reset $end
$scope module dut $end
$var wire 1 ( DA $end
$var wire 1 ) DB $end
$var wire 1 * DC $end
$var wire 1 + DD $end
$var wire 1 % X $end
$var wire 1 & clock $end
$var wire 1 ' reset $end
$var wire 1 ! D $end
$var wire 1 " C $end
$var wire 1 # B $end
$var wire 1 $ A $end
$scope module F1 $end
$var wire 1 ( D $end
$var wire 1 & clk $end
$var wire 1 ' rst $end
$var reg 1 $ Q $end
$upscope $end
$scope module F2 $end
$var wire 1 ) D $end
$var wire 1 & clk $end
$var wire 1 ' rst $end
$var reg 1 # Q $end
$upscope $end
$scope module F3 $end
$var wire 1 * D $end
$var wire 1 & clk $end
$var wire 1 ' rst $end
$var reg 1 " Q $end
$upscope $end
$scope module F4 $end
$var wire 1 + D $end
$var wire 1 & clk $end
$var wire 1 ' rst $end
$var reg 1 ! Q $end
$upscope $end
$upscope $end
$upscope $end
$enddefinitions $end
#0
$dumpvars
1+
0*
0)
0(
0'
0&
0%
0$
0#
0"
0!
$end
#5
1&
#10
0&
1'
#15
1*
0+
1!
1&
#20
0&
#25
1+
0!
1"
1&
#30
0&
#35
0*
0+
1)
1!
1&
#40
0&
#45
1+
1)
0!
0"
1#
1&
#50
0&
#55
1*
0+
1!
1&
#60
0&
#65
1+
0!
1"
1&
#70
0&
#75
0*
0)
1(
0+
1!
1&
#80
0&
#85
1+
0!
0"
0#
1$
1&
#90
0&
#95
0(
0+
1!
1&
#100
0&
#105
1+
0!
0$
1&
#110
1(
0&
1%
#115
0+
1$
1!
1&
#120
0&
#125
1)
1*
1+
0(
0!
1&
#130
0&
#135
1)
1*
0+
0(
0$
1#
1"
1!
1&
#140
0&
#145
0*
1+
0!
1&
#150
0&
#155
0*
0+
0"
1!
1&
#160
0&
#165
0)
1*
1+
0!
1&
#170
0&
#175
0)
1*
0+
0#
1"
1!
1&
#180
0&
#185
0*
1+
0!
1&
#190
0&
#195
0*
0+
0"
1!
1&
#200
0&
#205
1(
1+
0!
1&
